koba/__init__.py
koba/__main__.py
koba/main.py
koba/core/_unify_optim.c
koba/core/_unify_optim.cpython-39-x86_64-linux-gnu.so
koba/core/_unify_shared.py
koba/core/charsets.py
koba/core/core.py
koba/core/font.py
koba/core/unify.py
koba-0.6.2.dist-info/METADATA
koba-0.6.2.dist-info/WHEEL
koba-0.6.2.dist-info/entry_points.txt
koba-0.6.2.dist-info/top_level.txt
koba-0.6.2.dist-info/RECORD
koba-0.6.2.dist-info/licenses/LICENSE
