Metadata-Version: 2.4
Name: koba
Version: 0.6.2
Summary: Terminal Image/Video Renderer
Author-email: simon0302010 <simon0302010@gmail.com>
License-Expression: GPL-3.0-only
Project-URL: Homepage, https://github.com/simon0302010/koba
Classifier: Operating System :: POSIX :: Linux
Classifier: Operating System :: Microsoft :: Windows
Requires-Python: <4.0,>=3.9
License-File: LICENSE
Requires-Dist: numpy>=2.0.0
Requires-Dist: Pillow>=9.5.0
Requires-Dist: click>=8.0.0
Requires-Dist: matplotlib>=3.9.0
Requires-Dist: scikit-image>=0.24.0
Requires-Dist: tqdm>=4.67.1
Requires-Dist: fonttools>=4.58.0
Requires-Dist: moviepy>=2.0.0
Requires-Dist: rich>=13.0.0
Provides-Extra: test
Requires-Dist: pytest; extra == "test"
Requires-Dist: pytest-mock; extra == "test"
Dynamic: license-file
